pide/__init__.py
pide/inversion.py
pide/material.py
pide/model.py
pide/pide.py
pide/geodyn/__init__.py
pide/geodyn/deform_cond.py
pide/geodyn/geodyn_utils.py
pide/geodyn/geotherm.py
pide/geodyn/interpolate_fields.py
pide/geodyn/material_process.py
pide/geodyn/plot_models.py
pide/geodyn/read_uw_model.py
pide/geodyn/surface_cond.py
pide/geodyn/write_uw_model.py
pide/gravity/__init__.py
pide/gravity/grav.py
pide/imaging/__init__.py
pide/imaging/plot_distribution.py
pide/magnetic/__init__.py
pide/magnetic/mag.py
pide/mt/__init__.py
pide/mt/mt_model_conversion.py
pide/mt/mt_model_read.py
pide/pide_src/__init__.py
pide/pide_src/init_param.csv
pide/pide_src/materials.json
pide/pide_src/params.csv
pide/pide_src/water_calib.csv
pide/pide_src/cond_models/__init__.py
pide/pide_src/cond_models/fluids.csv
pide/pide_src/cond_models/fluids_odd.py
pide/pide_src/cond_models/melt.csv
pide/pide_src/cond_models/melt_odd.py
pide/pide_src/cond_models/minerals/__init__.py
pide/pide_src/cond_models/minerals/amp.csv
pide/pide_src/cond_models/minerals/amp_odd.py
pide/pide_src/cond_models/minerals/cpx.csv
pide/pide_src/cond_models/minerals/cpx_odd.py
pide/pide_src/cond_models/minerals/garnet.csv
pide/pide_src/cond_models/minerals/garnet_odd.py
pide/pide_src/cond_models/minerals/graphite.csv
pide/pide_src/cond_models/minerals/kfelds.csv
pide/pide_src/cond_models/minerals/kfelds_odd.py
pide/pide_src/cond_models/minerals/mica.csv
pide/pide_src/cond_models/minerals/mica_odd.py
pide/pide_src/cond_models/minerals/mixtures.csv
pide/pide_src/cond_models/minerals/mixtures_odd.py
pide/pide_src/cond_models/minerals/ol.csv
pide/pide_src/cond_models/minerals/ol_odd.py
pide/pide_src/cond_models/minerals/opx.csv
pide/pide_src/cond_models/minerals/opx_odd.py
pide/pide_src/cond_models/minerals/other.csv
pide/pide_src/cond_models/minerals/other_odd.py
pide/pide_src/cond_models/minerals/perov_odd.py
pide/pide_src/cond_models/minerals/perovskite.csv
pide/pide_src/cond_models/minerals/plag.csv
pide-1.1.0.dist-info/licenses/LICENSE
pide-1.1.0.dist-info/METADATA
pide-1.1.0.dist-info/WHEEL
pide-1.1.0.dist-info/top_level.txt
pide-1.1.0.dist-info/RECORD
