Metadata-Version: 2.4
Name: pide
Version: 1.1.0
Summary: A library for petrophysical interpretations of geophysical models.
Home-page: https://github.com/sinanozaydin/pide
Author: Sinan Ozaydin, Lu Li, Utpal Singh, Patrice F. Rey, Maria Constanza Manassero
Author-email: sinan.ozaydin@protonmail.com
License: GNU Lesser General Public License v3 (LGPLv3)
Keywords: petrophysics,geodynamic modelling,magnetotelluric,electrical conductivity,seismic velocity
Requires-Python: >3.8
License-File: LICENSE
Requires-Dist: numpy
Requires-Dist: matplotlib
Requires-Dist: scipy
Requires-Dist: santex>=1.2.2
Requires-Dist: h5py
Requires-Dist: harmonica
Requires-Dist: pyproj
Requires-Dist: netCDF4
Requires-Dist: psutil
Requires-Dist: burnman
Requires-Dist: CoolProp
Dynamic: author
Dynamic: author-email
Dynamic: home-page
Dynamic: keywords
Dynamic: license
Dynamic: license-file
Dynamic: requires-dist
Dynamic: requires-python
Dynamic: summary
